posts/__init__.py
posts/admin.py
posts/apps.py
posts/models.py
posts/version.py
posts/views.py
posts/templatetags/__init__.py
posts/templatetags/posts_tags.py
django_fluo_posts-0.2.2.dist-info/COPYING
django_fluo_posts-0.2.2.dist-info/METADATA
django_fluo_posts-0.2.2.dist-info/WHEEL
django_fluo_posts-0.2.2.dist-info/top_level.txt
django_fluo_posts-0.2.2.dist-info/RECORD
